{
  "annotations": {
    "list": [
      {
        "builtIn": 1,
        "datasource": {
          "type": "grafana",
          "uid": "-- Grafana --"
        },
        "enable": true,
        "hide": true,
        "iconColor": "rgba(0, 211, 255, 1)",
        "name": "Annotations & Alerts",
        "type": "dashboard"
      }
    ]
  },
  "editable": true,
  "fiscalYearStartMonth": 0,
  "graphTooltip": 0,
  "id": 63,
  "links": [],
  "liveNow": false,
  "panels": [
    {
      "collapsed": false,
      "gridPos": {
        "h": 1,
        "w": 24,
        "x": 0,
        "y": 0
      },
      "id": 16,
      "panels": [],
      "title": "Overview",
      "type": "row"
    },
    {
      "datasource": {
        "type": "prometheus",
        "uid": "prometheus"
      },
      "fieldConfig": {
        "defaults": {
          "color": {
            "mode": "fixed"
          },
          "fieldMinMax": false,
          "mappings": [],
          "noValue": "-",
          "thresholds": {
            "mode": "absolute",
            "steps": [
              {
                "color": "green",
                "value": null
              }
            ]
          },
          "unit": "bps"
        },
        "overrides": [
          {
            "matcher": {
              "id": "byName",
              "options": "Latency"
            },
            "properties": [
              {
                "id": "unit",
                "value": "ms"
              }
            ]
          }
        ]
      },
      "gridPos": {
        "h": 4,
        "w": 5,
        "x": 0,
        "y": 1
      },
      "id": 18,
      "options": {
        "colorMode": "none",
        "graphMode": "none",
        "justifyMode": "auto",
        "orientation": "auto",
        "reduceOptions": {
          "calcs": [
            "lastNotNull"
          ],
          "fields": "",
          "values": false
        },
        "textMode": "auto",
        "wideLayout": true
      },
      "pluginVersion": "10.2.2",
      "targets": [
        {
          "datasource": {
            "type": "prometheus",
            "uid": "prometheus"
          },
          "editorMode": "code",
          "exemplar": false,
          "expr": "speedtest_download_bits_per_second",
          "format": "time_series",
          "instant": false,
          "legendFormat": "Download",
          "range": true,
          "refId": "A"
        },
        {
          "datasource": {
            "type": "prometheus",
            "uid": "prometheus"
          },
          "editorMode": "code",
          "expr": "speedtest_upload_bits_per_second",
          "hide": false,
          "instant": false,
          "legendFormat": "Upload",
          "range": true,
          "refId": "B"
        },
        {
          "datasource": {
            "type": "prometheus",
            "uid": "prometheus"
          },
          "editorMode": "code",
          "expr": "speedtest_ping_latency_milliseconds",
          "hide": false,
          "instant": false,
          "legendFormat": "Latency",
          "range": true,
          "refId": "C"
        }
      ],
      "title": "Last WAN Speedtest",
      "type": "stat"
    },
    {
      "datasource": {
        "type": "prometheus",
        "uid": "prometheus"
      },
      "fieldConfig": {
        "defaults": {
          "color": {
            "mode": "fixed"
          },
          "fieldMinMax": false,
          "mappings": [],
          "noValue": "-",
          "thresholds": {
            "mode": "absolute",
            "steps": [
              {
                "color": "green",
                "value": null
              }
            ]
          },
          "unit": "bps"
        },
        "overrides": [
          {
            "matcher": {
              "id": "byName",
              "options": "Latency"
            },
            "properties": [
              {
                "id": "unit",
                "value": "ms"
              }
            ]
          }
        ]
      },
      "gridPos": {
        "h": 4,
        "w": 5,
        "x": 5,
        "y": 1
      },
      "id": 22,
      "options": {
        "colorMode": "none",
        "graphMode": "area",
        "justifyMode": "auto",
        "orientation": "auto",
        "reduceOptions": {
          "calcs": [
            "lastNotNull"
          ],
          "fields": "",
          "values": false
        },
        "textMode": "auto",
        "wideLayout": true
      },
      "pluginVersion": "10.2.2",
      "targets": [
        {
          "datasource": {
            "type": "prometheus",
            "uid": "prometheus"
          },
          "editorMode": "code",
          "expr": "(irate(node_network_receive_bytes_total{instance=\"opnsense.18b.lan:9100\",device=\"igc1\"}[5m]))*8",
          "instant": false,
          "legendFormat": "Down",
          "range": true,
          "refId": "A"
        },
        {
          "datasource": {
            "type": "prometheus",
            "uid": "prometheus"
          },
          "editorMode": "code",
          "expr": "(irate(node_network_transmit_bytes_total{instance=\"opnsense.18b.lan:9100\",device=\"igc1\"}[5m]))*8",
          "hide": false,
          "instant": false,
          "legendFormat": "Up",
          "range": true,
          "refId": "B"
        }
      ],
      "title": "WAN Network Traffic",
      "type": "stat"
    },
    {
      "datasource": {
        "type": "prometheus",
        "uid": "prometheus"
      },
      "description": "",
      "fieldConfig": {
        "defaults": {
          "color": {
            "mode": "thresholds"
          },
          "mappings": [
            {
              "options": {
                "0": {
                  "index": 1,
                  "text": "Down"
                },
                "1": {
                  "index": 0,
                  "text": "Up"
                }
              },
              "type": "value"
            }
          ],
          "thresholds": {
            "mode": "absolute",
            "steps": [
              {
                "color": "green",
                "value": null
              },
              {
                "color": "red",
                "value": 0
              },
              {
                "color": "green",
                "value": 1
              }
            ]
          }
        },
        "overrides": [
          {
            "matcher": {
              "id": "byName",
              "options": "Last Wireguard Handshake"
            },
            "properties": [
              {
                "id": "unit",
                "value": "dateTimeFromNow"
              }
            ]
          }
        ]
      },
      "gridPos": {
        "h": 4,
        "w": 4,
        "x": 10,
        "y": 1
      },
      "id": 23,
      "options": {
        "colorMode": "none",
        "graphMode": "none",
        "justifyMode": "auto",
        "orientation": "auto",
        "reduceOptions": {
          "calcs": [
            "lastNotNull"
          ],
          "fields": "",
          "values": false
        },
        "textMode": "value_and_name",
        "wideLayout": true
      },
      "pluginVersion": "10.2.2",
      "targets": [
        {
          "datasource": {
            "type": "prometheus",
            "uid": "Prometheus"
          },
          "editorMode": "code",
          "exemplar": true,
          "expr": "clamp_max(count(cloudflared_tunnel_ha_connections), 1)",
          "interval": "",
          "legendFormat": "Cloudflare Tunnel",
          "range": true,
          "refId": "A"
        },
        {
          "datasource": {
            "type": "prometheus",
            "uid": "prometheus"
          },
          "editorMode": "code",
          "expr": "wireguard_latest_handshake_seconds{public_key=\"EdmzcHAwnIn5Uv/SRDKBnwBUZIVxZ2MUnT7Ps/zFLHw=\"} * 1000",
          "hide": false,
          "instant": false,
          "legendFormat": "Last Wireguard Handshake",
          "range": true,
          "refId": "B"
        }
      ],
      "title": "Tunnels",
      "type": "stat"
    },
    {
      "datasource": {
        "type": "prometheus",
        "uid": "prometheus"
      },
      "fieldConfig": {
        "defaults": {
          "color": {
            "mode": "thresholds"
          },
          "mappings": [],
          "thresholds": {
            "mode": "absolute",
            "steps": [
              {
                "color": "green",
                "value": null
              }
            ]
          },
          "unit": "none"
        },
        "overrides": []
      },
      "gridPos": {
        "h": 4,
        "w": 3,
        "x": 14,
        "y": 1
      },
      "id": 19,
      "options": {
        "colorMode": "none",
        "graphMode": "none",
        "justifyMode": "auto",
        "orientation": "auto",
        "reduceOptions": {
          "calcs": [
            "lastNotNull"
          ],
          "fields": "",
          "values": false
        },
        "textMode": "auto",
        "wideLayout": true
      },
      "pluginVersion": "10.2.2",
      "targets": [
        {
          "datasource": {
            "type": "prometheus",
            "uid": "prometheus"
          },
          "editorMode": "code",
          "expr": "count(pve_up == 1 and on(id) pve_guest_info)",
          "instant": false,
          "legendFormat": "Running",
          "range": true,
          "refId": "A"
        },
        {
          "datasource": {
            "type": "prometheus",
            "uid": "prometheus"
          },
          "editorMode": "code",
          "expr": "count(pve_up == 0 and on(id) pve_guest_info)",
          "hide": false,
          "instant": false,
          "legendFormat": "Stopped",
          "range": true,
          "refId": "B"
        }
      ],
      "title": "Virtual Machines",
      "type": "stat"
    },
    {
      "datasource": {
        "type": "prometheus",
        "uid": "prometheus"
      },
      "fieldConfig": {
        "defaults": {
          "color": {
            "mode": "thresholds"
          },
          "mappings": [],
          "thresholds": {
            "mode": "absolute",
            "steps": [
              {
                "color": "green",
                "value": null
              }
            ]
          },
          "unit": "none"
        },
        "overrides": []
      },
      "gridPos": {
        "h": 4,
        "w": 3,
        "x": 17,
        "y": 1
      },
      "id": 24,
      "options": {
        "colorMode": "none",
        "graphMode": "none",
        "justifyMode": "auto",
        "orientation": "auto",
        "reduceOptions": {
          "calcs": [
            "lastNotNull"
          ],
          "fields": "",
          "values": false
        },
        "textMode": "auto",
        "wideLayout": true
      },
      "pluginVersion": "10.2.2",
      "targets": [
        {
          "datasource": {
            "type": "prometheus",
            "uid": "prometheus"
          },
          "editorMode": "code",
          "expr": "count(unpoller_device_info{type=\"uap\"})",
          "instant": false,
          "legendFormat": "APs",
          "range": true,
          "refId": "A"
        },
        {
          "datasource": {
            "type": "prometheus",
            "uid": "prometheus"
          },
          "editorMode": "code",
          "expr": "count(unpoller_device_info{type=\"usw\"})",
          "hide": false,
          "instant": false,
          "legendFormat": "Switches",
          "range": true,
          "refId": "B"
        }
      ],
      "title": "UniFi Devices",
      "type": "stat"
    },
    {
      "datasource": {
        "type": "prometheus",
        "uid": "prometheus"
      },
      "fieldConfig": {
        "defaults": {
          "color": {
            "mode": "fixed"
          },
          "mappings": [],
          "thresholds": {
            "mode": "absolute",
            "steps": [
              {
                "color": "green",
                "value": null
              }
            ]
          }
        },
        "overrides": []
      },
      "gridPos": {
        "h": 4,
        "w": 4,
        "x": 20,
        "y": 1
      },
      "id": 17,
      "options": {
        "colorMode": "none",
        "graphMode": "area",
        "justifyMode": "auto",
        "orientation": "auto",
        "reduceOptions": {
          "calcs": [
            "lastNotNull"
          ],
          "fields": "",
          "values": false
        },
        "textMode": "auto",
        "wideLayout": true
      },
      "pluginVersion": "10.2.2",
      "targets": [
        {
          "datasource": {
            "type": "prometheus",
            "uid": "prometheus"
          },
          "editorMode": "code",
          "expr": "count(unpoller_client_uptime_seconds{wired=\"true\"} > 0)",
          "instant": false,
          "legendFormat": "Wired",
          "range": true,
          "refId": "A"
        },
        {
          "datasource": {
            "type": "prometheus",
            "uid": "prometheus"
          },
          "editorMode": "code",
          "expr": "count(unpoller_client_uptime_seconds{wired=\"false\"} > 0)",
          "hide": false,
          "instant": false,
          "legendFormat": "Wireless",
          "range": true,
          "refId": "B"
        }
      ],
      "title": "UniFi Clients",
      "type": "stat"
    },
    {
      "collapsed": false,
      "gridPos": {
        "h": 1,
        "w": 24,
        "x": 0,
        "y": 5
      },
      "id": 3,
      "panels": [],
      "title": "Nodes",
      "type": "row"
    },
    {
      "datasource": {
        "type": "prometheus",
        "uid": "prometheus"
      },
      "fieldConfig": {
        "defaults": {
          "color": {
            "mode": "palette-classic"
          },
          "custom": {
            "axisBorderShow": false,
            "axisCenteredZero": false,
            "axisColorMode": "text",
            "axisLabel": "",
            "axisPlacement": "auto",
            "barAlignment": 0,
            "drawStyle": "line",
            "fillOpacity": 5,
            "gradientMode": "none",
            "hideFrom": {
              "legend": false,
              "tooltip": false,
              "viz": false
            },
            "insertNulls": false,
            "lineInterpolation": "linear",
            "lineWidth": 1,
            "pointSize": 1,
            "scaleDistribution": {
              "type": "linear"
            },
            "showPoints": "auto",
            "spanNulls": false,
            "stacking": {
              "group": "A",
              "mode": "none"
            },
            "thresholdsStyle": {
              "mode": "off"
            }
          },
          "mappings": [],
          "max": 100,
          "min": 0,
          "thresholds": {
            "mode": "absolute",
            "steps": [
              {
                "color": "green",
                "value": null
              },
              {
                "color": "red",
                "value": 80
              }
            ]
          },
          "unit": "percent"
        },
        "overrides": []
      },
      "gridPos": {
        "h": 9,
        "w": 12,
        "x": 0,
        "y": 6
      },
      "id": 5,
      "options": {
        "legend": {
          "calcs": [
            "mean",
            "min",
            "max",
            "lastNotNull"
          ],
          "displayMode": "table",
          "placement": "right",
          "showLegend": true,
          "sortBy": "Last *",
          "sortDesc": true
        },
        "tooltip": {
          "mode": "single",
          "sort": "none"
        }
      },
      "targets": [
        {
          "datasource": {
            "type": "prometheus",
            "uid": "prometheus"
          },
          "editorMode": "code",
          "expr": "((sum by(instance) (irate(node_cpu_seconds_total{mode!=\"idle\"}[$__rate_interval])) / on(instance) group_left sum by (instance)((irate(node_cpu_seconds_total{}[$__rate_interval])))) * 100) + on(instance) group_left(nodename) (0* node_uname_info{})",
          "instant": false,
          "legendFormat": "{{nodename}}",
          "range": true,
          "refId": "A"
        }
      ],
      "title": "CPU Usage",
      "type": "timeseries"
    },
    {
      "datasource": {
        "type": "prometheus",
        "uid": "prometheus"
      },
      "fieldConfig": {
        "defaults": {
          "color": {
            "mode": "palette-classic"
          },
          "custom": {
            "axisBorderShow": false,
            "axisCenteredZero": false,
            "axisColorMode": "text",
            "axisLabel": "",
            "axisPlacement": "auto",
            "barAlignment": 0,
            "drawStyle": "line",
            "fillOpacity": 5,
            "gradientMode": "none",
            "hideFrom": {
              "legend": false,
              "tooltip": false,
              "viz": false
            },
            "insertNulls": false,
            "lineInterpolation": "linear",
            "lineWidth": 1,
            "pointSize": 1,
            "scaleDistribution": {
              "type": "linear"
            },
            "showPoints": "auto",
            "spanNulls": false,
            "stacking": {
              "group": "A",
              "mode": "none"
            },
            "thresholdsStyle": {
              "mode": "off"
            }
          },
          "mappings": [],
          "thresholds": {
            "mode": "absolute",
            "steps": [
              {
                "color": "green",
                "value": null
              },
              {
                "color": "red",
                "value": 80
              }
            ]
          },
          "unit": "none"
        },
        "overrides": []
      },
      "gridPos": {
        "h": 9,
        "w": 12,
        "x": 12,
        "y": 6
      },
      "id": 8,
      "options": {
        "legend": {
          "calcs": [
            "mean",
            "min",
            "max",
            "lastNotNull"
          ],
          "displayMode": "table",
          "placement": "right",
          "showLegend": true
        },
        "tooltip": {
          "mode": "single",
          "sort": "none"
        }
      },
      "targets": [
        {
          "datasource": {
            "type": "prometheus",
            "uid": "prometheus"
          },
          "editorMode": "code",
          "expr": "(avg_over_time(node_load5{}[$__rate_interval]) / on(instance) group_left sum by (instance)(irate(node_cpu_seconds_total{}[$__rate_interval]))) + on(instance) group_left(nodename) (0* node_uname_info{})",
          "instant": false,
          "legendFormat": "{{nodename}}",
          "range": true,
          "refId": "A"
        }
      ],
      "title": "System Load (load5)",
      "type": "timeseries"
    },
    {
      "datasource": {
        "type": "prometheus",
        "uid": "prometheus"
      },
      "fieldConfig": {
        "defaults": {
          "color": {
            "mode": "palette-classic"
          },
          "custom": {
            "axisBorderShow": false,
            "axisCenteredZero": false,
            "axisColorMode": "text",
            "axisLabel": "",
            "axisPlacement": "auto",
            "barAlignment": 0,
            "drawStyle": "line",
            "fillOpacity": 5,
            "gradientMode": "none",
            "hideFrom": {
              "legend": false,
              "tooltip": false,
              "viz": false
            },
            "insertNulls": false,
            "lineInterpolation": "linear",
            "lineWidth": 1,
            "pointSize": 1,
            "scaleDistribution": {
              "type": "linear"
            },
            "showPoints": "auto",
            "spanNulls": false,
            "stacking": {
              "group": "A",
              "mode": "none"
            },
            "thresholdsStyle": {
              "mode": "off"
            }
          },
          "mappings": [],
          "max": 100,
          "min": 0,
          "thresholds": {
            "mode": "absolute",
            "steps": [
              {
                "color": "green",
                "value": null
              },
              {
                "color": "red",
                "value": 80
              }
            ]
          },
          "unit": "percent"
        },
        "overrides": []
      },
      "gridPos": {
        "h": 9,
        "w": 12,
        "x": 0,
        "y": 15
      },
      "id": 6,
      "options": {
        "legend": {
          "calcs": [
            "mean",
            "min",
            "max",
            "lastNotNull"
          ],
          "displayMode": "table",
          "placement": "right",
          "showLegend": true,
          "sortBy": "Last *",
          "sortDesc": true
        },
        "tooltip": {
          "mode": "single",
          "sort": "none"
        }
      },
      "targets": [
        {
          "datasource": {
            "type": "prometheus",
            "uid": "prometheus"
          },
          "editorMode": "code",
          "expr": "((((avg_over_time(node_memory_MemTotal_bytes{}[$__rate_interval]) - avg_over_time(node_memory_MemAvailable_bytes{}[$__rate_interval])) / avg_over_time(node_memory_MemTotal_bytes{}[$__rate_interval])) * 100) or (((avg_over_time(node_memory_active_bytes{}[$__rate_interval]) + avg_over_time(node_memory_wired_bytes{}[$__rate_interval])) / avg_over_time(node_memory_size_bytes{}[$__rate_interval])) * 100)) + on(instance) group_left(nodename) (0* node_uname_info{})",
          "instant": false,
          "legendFormat": "{{nodename}}",
          "range": true,
          "refId": "A"
        }
      ],
      "title": "Memory Usage",
      "type": "timeseries"
    },
    {
      "datasource": {
        "type": "prometheus",
        "uid": "prometheus"
      },
      "fieldConfig": {
        "defaults": {
          "color": {
            "mode": "palette-classic"
          },
          "custom": {
            "axisBorderShow": false,
            "axisCenteredZero": false,
            "axisColorMode": "text",
            "axisLabel": "Bites out (-) / in (+)",
            "axisPlacement": "auto",
            "barAlignment": 0,
            "drawStyle": "line",
            "fillOpacity": 40,
            "gradientMode": "none",
            "hideFrom": {
              "legend": false,
              "tooltip": false,
              "viz": false
            },
            "insertNulls": false,
            "lineInterpolation": "linear",
            "lineWidth": 1,
            "pointSize": 5,
            "scaleDistribution": {
              "type": "linear"
            },
            "showPoints": "never",
            "spanNulls": false,
            "stacking": {
              "group": "A",
              "mode": "none"
            },
            "thresholdsStyle": {
              "mode": "off"
            }
          },
          "links": [],
          "mappings": [],
          "thresholds": {
            "mode": "absolute",
            "steps": [
              {
                "color": "green",
                "value": null
              },
              {
                "color": "red",
                "value": 80
              }
            ]
          },
          "unit": "bps"
        },
        "overrides": [
          {
            "matcher": {
              "id": "byName",
              "options": "receive_packets_eth0"
            },
            "properties": [
              {
                "id": "color",
                "value": {
                  "fixedColor": "#7EB26D",
                  "mode": "fixed"
                }
              }
            ]
          },
          {
            "matcher": {
              "id": "byName",
              "options": "receive_packets_lo"
            },
            "properties": [
              {
                "id": "color",
                "value": {
                  "fixedColor": "#E24D42",
                  "mode": "fixed"
                }
              }
            ]
          },
          {
            "matcher": {
              "id": "byName",
              "options": "transmit_packets_eth0"
            },
            "properties": [
              {
                "id": "color",
                "value": {
                  "fixedColor": "#7EB26D",
                  "mode": "fixed"
                }
              }
            ]
          },
          {
            "matcher": {
              "id": "byName",
              "options": "transmit_packets_lo"
            },
            "properties": [
              {
                "id": "color",
                "value": {
                  "fixedColor": "#E24D42",
                  "mode": "fixed"
                }
              }
            ]
          },
          {
            "matcher": {
              "id": "byRegexp",
              "options": "/.*Trans.*/"
            },
            "properties": [
              {
                "id": "custom.transform",
                "value": "negative-Y"
              }
            ]
          },
          {
            "matcher": {
              "id": "byRegexp",
              "options": "/.*lo0.*/"
            },
            "properties": [
              {
                "id": "color",
                "value": {
                  "fixedColor": "#7EB26D",
                  "mode": "fixed"
                }
              }
            ]
          },
          {
            "matcher": {
              "id": "byRegexp",
              "options": "/.*lo1.*/"
            },
            "properties": [
              {
                "id": "color",
                "value": {
                  "fixedColor": "#EAB839",
                  "mode": "fixed"
                }
              }
            ]
          },
          {
            "matcher": {
              "id": "byRegexp",
              "options": "/.*em0.*/"
            },
            "properties": [
              {
                "id": "color",
                "value": {
                  "fixedColor": "#EF843C",
                  "mode": "fixed"
                }
              }
            ]
          },
          {
            "matcher": {
              "id": "byRegexp",
              "options": "/.*em1.*/"
            },
            "properties": [
              {
                "id": "color",
                "value": {
                  "fixedColor": "#E24D42",
                  "mode": "fixed"
                }
              }
            ]
          }
        ]
      },
      "gridPos": {
        "h": 9,
        "w": 12,
        "x": 12,
        "y": 15
      },
      "id": 7,
      "links": [],
      "options": {
        "legend": {
          "calcs": [
            "mean",
            "min",
            "max",
            "lastNotNull"
          ],
          "displayMode": "table",
          "placement": "right",
          "showLegend": true,
          "sortBy": "Last *",
          "sortDesc": true
        },
        "tooltip": {
          "mode": "multi",
          "sort": "none"
        }
      },
      "pluginVersion": "9.2.0",
      "targets": [
        {
          "datasource": {
            "type": "prometheus",
            "uid": "Prometheus"
          },
          "editorMode": "code",
          "expr": "(sum(irate(node_network_receive_bytes_total{}[5m])*8) by(instance)) + on(instance) group_left(nodename) (0* node_uname_info{})",
          "format": "time_series",
          "intervalFactor": 2,
          "legendFormat": "{{nodename}} - Receive",
          "range": true,
          "refId": "O",
          "step": 240
        },
        {
          "datasource": {
            "type": "prometheus",
            "uid": "Prometheus"
          },
          "editorMode": "code",
          "expr": "(sum(irate(node_network_transmit_bytes_total{}[5m])*8) by(instance)) + on(instance) group_left(nodename) (0* node_uname_info{})",
          "format": "time_series",
          "intervalFactor": 2,
          "legendFormat": "{{nodename}} - Transmit",
          "range": true,
          "refId": "P",
          "step": 240
        }
      ],
      "title": "Network Traffic",
      "type": "timeseries"
    },
    {
      "datasource": {
        "type": "prometheus",
        "uid": "prometheus"
      },
      "fieldConfig": {
        "defaults": {
          "color": {
            "mode": "palette-classic"
          },
          "custom": {
            "axisBorderShow": false,
            "axisCenteredZero": false,
            "axisColorMode": "text",
            "axisLabel": "",
            "axisPlacement": "auto",
            "barAlignment": 0,
            "drawStyle": "line",
            "fillOpacity": 5,
            "gradientMode": "none",
            "hideFrom": {
              "legend": false,
              "tooltip": false,
              "viz": false
            },
            "insertNulls": false,
            "lineInterpolation": "linear",
            "lineWidth": 1,
            "pointSize": 1,
            "scaleDistribution": {
              "type": "linear"
            },
            "showPoints": "auto",
            "spanNulls": false,
            "stacking": {
              "group": "A",
              "mode": "none"
            },
            "thresholdsStyle": {
              "mode": "off"
            }
          },
          "mappings": [],
          "max": 100,
          "min": 0,
          "thresholds": {
            "mode": "absolute",
            "steps": [
              {
                "color": "green",
                "value": null
              },
              {
                "color": "red",
                "value": 80
              }
            ]
          },
          "unit": "percent"
        },
        "overrides": []
      },
      "gridPos": {
        "h": 9,
        "w": 12,
        "x": 0,
        "y": 24
      },
      "id": 9,
      "options": {
        "legend": {
          "calcs": [
            "mean",
            "min",
            "max",
            "lastNotNull"
          ],
          "displayMode": "table",
          "placement": "right",
          "showLegend": true,
          "sortBy": "Last *",
          "sortDesc": true
        },
        "tooltip": {
          "mode": "single",
          "sort": "none"
        }
      },
      "targets": [
        {
          "datasource": {
            "type": "prometheus",
            "uid": "prometheus"
          },
          "editorMode": "code",
          "expr": "(100 - ((avg_over_time(node_filesystem_avail_bytes{mountpoint=\"/\"}[$__rate_interval]) * 100) / avg_over_time(node_filesystem_size_bytes{mountpoint=\"/\"}[$__rate_interval]))) + on(instance) group_left(nodename) (0* node_uname_info{})",
          "instant": false,
          "legendFormat": "{{nodename}}",
          "range": true,
          "refId": "A"
        }
      ],
      "title": "Root Filesystem Usage",
      "type": "timeseries"
    },
    {
      "collapsed": false,
      "gridPos": {
        "h": 1,
        "w": 24,
        "x": 0,
        "y": 33
      },
      "id": 10,
      "panels": [],
      "title": "UniFi Devices",
      "type": "row"
    },
    {
      "datasource": {
        "type": "prometheus",
        "uid": "prometheus"
      },
      "fieldConfig": {
        "defaults": {
          "color": {
            "mode": "palette-classic"
          },
          "custom": {
            "axisBorderShow": false,
            "axisCenteredZero": false,
            "axisColorMode": "text",
            "axisLabel": "",
            "axisPlacement": "auto",
            "barAlignment": 0,
            "drawStyle": "line",
            "fillOpacity": 5,
            "gradientMode": "none",
            "hideFrom": {
              "legend": false,
              "tooltip": false,
              "viz": false
            },
            "insertNulls": false,
            "lineInterpolation": "linear",
            "lineWidth": 1,
            "pointSize": 1,
            "scaleDistribution": {
              "type": "linear"
            },
            "showPoints": "auto",
            "spanNulls": false,
            "stacking": {
              "group": "A",
              "mode": "none"
            },
            "thresholdsStyle": {
              "mode": "off"
            }
          },
          "mappings": [],
          "max": 1,
          "min": 0,
          "thresholds": {
            "mode": "absolute",
            "steps": [
              {
                "color": "green",
                "value": null
              },
              {
                "color": "red",
                "value": 80
              }
            ]
          },
          "unit": "percentunit"
        },
        "overrides": []
      },
      "gridPos": {
        "h": 9,
        "w": 12,
        "x": 0,
        "y": 34
      },
      "id": 13,
      "options": {
        "legend": {
          "calcs": [
            "mean",
            "min",
            "max",
            "lastNotNull"
          ],
          "displayMode": "table",
          "placement": "right",
          "showLegend": true,
          "sortBy": "Last *",
          "sortDesc": true
        },
        "tooltip": {
          "mode": "single",
          "sort": "none"
        }
      },
      "targets": [
        {
          "datasource": {
            "type": "prometheus",
            "uid": "prometheus"
          },
          "editorMode": "code",
          "expr": "unpoller_device_cpu_utilization_ratio{}",
          "instant": false,
          "legendFormat": "{{name}}",
          "range": true,
          "refId": "A"
        }
      ],
      "title": "CPU Usage",
      "type": "timeseries"
    },
    {
      "datasource": {
        "type": "prometheus",
        "uid": "prometheus"
      },
      "fieldConfig": {
        "defaults": {
          "color": {
            "mode": "palette-classic"
          },
          "custom": {
            "axisBorderShow": false,
            "axisCenteredZero": false,
            "axisColorMode": "text",
            "axisLabel": "",
            "axisPlacement": "auto",
            "barAlignment": 0,
            "drawStyle": "line",
            "fillOpacity": 5,
            "gradientMode": "none",
            "hideFrom": {
              "legend": false,
              "tooltip": false,
              "viz": false
            },
            "insertNulls": false,
            "lineInterpolation": "linear",
            "lineWidth": 1,
            "pointSize": 1,
            "scaleDistribution": {
              "type": "linear"
            },
            "showPoints": "auto",
            "spanNulls": false,
            "stacking": {
              "group": "A",
              "mode": "none"
            },
            "thresholdsStyle": {
              "mode": "off"
            }
          },
          "mappings": [],
          "thresholds": {
            "mode": "absolute",
            "steps": [
              {
                "color": "green",
                "value": null
              },
              {
                "color": "red",
                "value": 80
              }
            ]
          },
          "unit": "none"
        },
        "overrides": []
      },
      "gridPos": {
        "h": 9,
        "w": 12,
        "x": 12,
        "y": 34
      },
      "id": 14,
      "options": {
        "legend": {
          "calcs": [
            "mean",
            "min",
            "max",
            "lastNotNull"
          ],
          "displayMode": "table",
          "placement": "right",
          "showLegend": true
        },
        "tooltip": {
          "mode": "single",
          "sort": "none"
        }
      },
      "targets": [
        {
          "datasource": {
            "type": "prometheus",
            "uid": "prometheus"
          },
          "editorMode": "code",
          "expr": "unpoller_device_load_average_5{}",
          "instant": false,
          "legendFormat": "{{name}}",
          "range": true,
          "refId": "A"
        }
      ],
      "title": "System Load (load5)",
      "type": "timeseries"
    },
    {
      "datasource": {
        "type": "prometheus",
        "uid": "prometheus"
      },
      "fieldConfig": {
        "defaults": {
          "color": {
            "mode": "palette-classic"
          },
          "custom": {
            "axisBorderShow": false,
            "axisCenteredZero": false,
            "axisColorMode": "text",
            "axisLabel": "",
            "axisPlacement": "auto",
            "barAlignment": 0,
            "drawStyle": "line",
            "fillOpacity": 5,
            "gradientMode": "none",
            "hideFrom": {
              "legend": false,
              "tooltip": false,
              "viz": false
            },
            "insertNulls": false,
            "lineInterpolation": "linear",
            "lineWidth": 1,
            "pointSize": 1,
            "scaleDistribution": {
              "type": "linear"
            },
            "showPoints": "auto",
            "spanNulls": false,
            "stacking": {
              "group": "A",
              "mode": "none"
            },
            "thresholdsStyle": {
              "mode": "off"
            }
          },
          "mappings": [],
          "max": 1,
          "min": 0,
          "thresholds": {
            "mode": "absolute",
            "steps": [
              {
                "color": "green",
                "value": null
              },
              {
                "color": "red",
                "value": 80
              }
            ]
          },
          "unit": "percentunit"
        },
        "overrides": []
      },
      "gridPos": {
        "h": 9,
        "w": 12,
        "x": 0,
        "y": 43
      },
      "id": 12,
      "options": {
        "legend": {
          "calcs": [
            "mean",
            "min",
            "max",
            "lastNotNull"
          ],
          "displayMode": "table",
          "placement": "right",
          "showLegend": true,
          "sortBy": "Last *",
          "sortDesc": true
        },
        "tooltip": {
          "mode": "single",
          "sort": "none"
        }
      },
      "targets": [
        {
          "datasource": {
            "type": "prometheus",
            "uid": "prometheus"
          },
          "editorMode": "code",
          "expr": "unpoller_device_memory_utilization_ratio{}",
          "instant": false,
          "legendFormat": "{{name}}",
          "range": true,
          "refId": "A"
        }
      ],
      "title": "Memory Usage",
      "type": "timeseries"
    },
    {
      "datasource": {
        "type": "prometheus",
        "uid": "prometheus"
      },
      "fieldConfig": {
        "defaults": {
          "color": {
            "mode": "palette-classic"
          },
          "custom": {
            "axisBorderShow": false,
            "axisCenteredZero": false,
            "axisColorMode": "text",
            "axisLabel": "Bites out (-) / in (+)",
            "axisPlacement": "auto",
            "barAlignment": 0,
            "drawStyle": "line",
            "fillOpacity": 40,
            "gradientMode": "none",
            "hideFrom": {
              "legend": false,
              "tooltip": false,
              "viz": false
            },
            "insertNulls": false,
            "lineInterpolation": "linear",
            "lineWidth": 1,
            "pointSize": 5,
            "scaleDistribution": {
              "type": "linear"
            },
            "showPoints": "never",
            "spanNulls": false,
            "stacking": {
              "group": "A",
              "mode": "none"
            },
            "thresholdsStyle": {
              "mode": "off"
            }
          },
          "links": [],
          "mappings": [],
          "thresholds": {
            "mode": "absolute",
            "steps": [
              {
                "color": "green",
                "value": null
              },
              {
                "color": "red",
                "value": 80
              }
            ]
          },
          "unit": "bps"
        },
        "overrides": [
          {
            "matcher": {
              "id": "byName",
              "options": "receive_packets_eth0"
            },
            "properties": [
              {
                "id": "color",
                "value": {
                  "fixedColor": "#7EB26D",
                  "mode": "fixed"
                }
              }
            ]
          },
          {
            "matcher": {
              "id": "byName",
              "options": "receive_packets_lo"
            },
            "properties": [
              {
                "id": "color",
                "value": {
                  "fixedColor": "#E24D42",
                  "mode": "fixed"
                }
              }
            ]
          },
          {
            "matcher": {
              "id": "byName",
              "options": "transmit_packets_eth0"
            },
            "properties": [
              {
                "id": "color",
                "value": {
                  "fixedColor": "#7EB26D",
                  "mode": "fixed"
                }
              }
            ]
          },
          {
            "matcher": {
              "id": "byName",
              "options": "transmit_packets_lo"
            },
            "properties": [
              {
                "id": "color",
                "value": {
                  "fixedColor": "#E24D42",
                  "mode": "fixed"
                }
              }
            ]
          },
          {
            "matcher": {
              "id": "byRegexp",
              "options": "/.*Trans.*/"
            },
            "properties": [
              {
                "id": "custom.transform",
                "value": "negative-Y"
              }
            ]
          },
          {
            "matcher": {
              "id": "byRegexp",
              "options": "/.*lo0.*/"
            },
            "properties": [
              {
                "id": "color",
                "value": {
                  "fixedColor": "#7EB26D",
                  "mode": "fixed"
                }
              }
            ]
          },
          {
            "matcher": {
              "id": "byRegexp",
              "options": "/.*lo1.*/"
            },
            "properties": [
              {
                "id": "color",
                "value": {
                  "fixedColor": "#EAB839",
                  "mode": "fixed"
                }
              }
            ]
          },
          {
            "matcher": {
              "id": "byRegexp",
              "options": "/.*em0.*/"
            },
            "properties": [
              {
                "id": "color",
                "value": {
                  "fixedColor": "#EF843C",
                  "mode": "fixed"
                }
              }
            ]
          },
          {
            "matcher": {
              "id": "byRegexp",
              "options": "/.*em1.*/"
            },
            "properties": [
              {
                "id": "color",
                "value": {
                  "fixedColor": "#E24D42",
                  "mode": "fixed"
                }
              }
            ]
          }
        ]
      },
      "gridPos": {
        "h": 9,
        "w": 12,
        "x": 12,
        "y": 43
      },
      "id": 15,
      "links": [],
      "options": {
        "legend": {
          "calcs": [
            "mean",
            "min",
            "max",
            "lastNotNull"
          ],
          "displayMode": "table",
          "placement": "right",
          "showLegend": true,
          "sortBy": "Last *",
          "sortDesc": true
        },
        "tooltip": {
          "mode": "multi",
          "sort": "none"
        }
      },
      "pluginVersion": "9.2.0",
      "targets": [
        {
          "datasource": {
            "type": "prometheus",
            "uid": "Prometheus"
          },
          "editorMode": "code",
          "expr": "sum(rate(unpoller_device_port_receive_bytes_total{}[5m])) by (name) or sum(rate(unpoller_device_receive_bytes_total{}[5m])) by (name)",
          "format": "time_series",
          "intervalFactor": 2,
          "legendFormat": "{{name}} - Receive",
          "range": true,
          "refId": "O",
          "step": 240
        },
        {
          "datasource": {
            "type": "prometheus",
            "uid": "Prometheus"
          },
          "editorMode": "code",
          "expr": "sum(rate(unpoller_device_port_transmit_bytes_total{}[5m])) by (name) or sum(rate(unpoller_device_transmit_bytes_total{}[5m])) by (name)",
          "format": "time_series",
          "intervalFactor": 2,
          "legendFormat": "{{name}} - Transmit",
          "range": true,
          "refId": "P",
          "step": 240
        }
      ],
      "title": "Network Traffic",
      "type": "timeseries"
    }
  ],
  "refresh": "",
  "schemaVersion": 38,
  "tags": [],
  "templating": {
    "list": []
  },
  "time": {
    "from": "now-3h",
    "to": "now"
  },
  "timepicker": {},
  "timezone": "",
  "title": "Homelab Overview",
  "uid": "a0bbbc12-4b43-40a7-89fe-2ce7b62730be",
  "version": 6,
  "weekStart": ""
}
